{
	"name":			"account",
	"version":		1,
	"description":	"Account components: registration, login, account settings...",
	"dependencies": {
		"api":		"latest",
		"formjs":	"latest"
	},
	"install":	{
		
	},
	"server":	{
		"endpoints":	[
			"server/user.js"
		]
	},
	"client":	{
		"bower":	{
			"jquery":		"latest",
			"bootstrap":	"latest"
		},
		"files":	[
			"client/events/events.js",
			"client/forms/register.js",
			"client/forms/login.js",
			"client/forms/edit.js",
			"client/actions/logout.js"
		]
	}
}